LICENSE
MANIFEST.in
README.md
setup.py
django_reverse_admin/__init__.py
django_reverse_admin.egg-info/PKG-INFO
django_reverse_admin.egg-info/SOURCES.txt
django_reverse_admin.egg-info/dependency_links.txt
django_reverse_admin.egg-info/top_level.txt
images/admin_with_reverse_inline_1.png
images/admin_with_reverse_inline_2.png
images/admin_without_reverse_inline.png