Metadata-Version: 2.1
Name: django-reverse-admin
Version: 2.9.4
Summary: UNKNOWN
Home-page: UNKNOWN
License: BSD
Platform: UNKNOWN
Classifier: License :: OSI Approved :: BSD License
Requires-Python: >=3
